convertextract/__init__.py
convertextract/cli.py
convertextract/colors.py
convertextract/exceptions.py
convertextract/gui.py
convertextract/parsers/__init__.py
convertextract/parsers/csv_parser.py
convertextract/parsers/docx_parser.py
convertextract/parsers/eaf_parser.py
convertextract/parsers/html_parser.py
convertextract/parsers/json_parser.py
convertextract/parsers/pptx_parser.py
convertextract/parsers/psv_parser.py
convertextract/parsers/tsv_parser.py
convertextract/parsers/txt_parser.py
convertextract/parsers/utils.py
convertextract/parsers/xlsx_parser.py
convertextract-3.2.17.data/scripts/convertextract
convertextract-3.2.17.dist-info/LICENSE
convertextract-3.2.17.dist-info/METADATA
convertextract-3.2.17.dist-info/WHEEL
convertextract-3.2.17.dist-info/top_level.txt
convertextract-3.2.17.dist-info/RECORD
