Metadata-Version: 2.1
Name: convertextract
Version: 3.2.17
Summary: Arbitrary transliterations on Microsoft Office documents
Home-page: https://github.com/roedoejet/convertextract
Download-URL: https://github.com/roedoejet/convertextract/archives/master
Author: Aidan Pine
Author-email: info@mothertongues.org
License: MIT
Requires-Python: >3.4
License-File: LICENSE
Requires-Dist: argcomplete (==1.8.2)
Requires-Dist: chardet (==3.0.4)
Requires-Dist: python-pptx (==0.6.6)
Requires-Dist: beautifulsoup4 (==4.6.0)
Requires-Dist: python-docx (==0.8.6)
Requires-Dist: xlrd (==1.0.0)
Requires-Dist: openpyxl
Requires-Dist: pympi-ling (>=1.69)
Requires-Dist: six (>=1.10.0)
Requires-Dist: g2p (>=0.4)
